p10s/__init__.py
p10s/__version__.py
p10s/base.py
p10s/config_context.py
p10s/generator.py
p10s/kubernetes.py
p10s/loads.py
p10s/terraform.py
p10s/utils.py
p10s/values.py
p10s/watcher.py
pyterranetes-0.11.1.data/scripts/p10s
pyterranetes-0.11.1.dist-info/METADATA
pyterranetes-0.11.1.dist-info/WHEEL
pyterranetes-0.11.1.dist-info/top_level.txt
pyterranetes-0.11.1.dist-info/RECORD
