Metadata-Version: 2.1
Name: pyterranetes
Version: 0.11.1
Summary: A toolkit for reducing duplication in terraform and k8s code.
Home-page: https://segv.gitlab.io/pyterranetes/
Author: Marco Baringer
Author-email: mb@bese.it
License: MIT
Platform: UNKNOWN
Classifier: License :: OSI Approved :: MIT License
Classifier: Programming Language :: Python
Classifier: Programming Language :: Python :: 3
Classifier: Programming Language :: Python :: 3.6
Classifier: Programming Language :: Python :: 3.7
Classifier: Programming Language :: Python :: 3.8
Classifier: Programming Language :: Python :: 3.9
Requires-Python: >=3.8.0
Requires-Dist: Click (>=8.0.0)
Requires-Dist: ruamel.yaml (>=0.16.13)
Requires-Dist: pyhcl (>=0.4.4)
Requires-Dist: watchdog (>=1.0.0)
